DFF2rx.v
module DFF2rx(
input D,clk
output reg Q
);

always @(posedge clk)
begin
    Q=D;
end

endmodule

uart_rx.v
module SIPO(
    input clk,          //driven by tick!
    input data_in,
    output a, b, c, d, e, f, g, h
);

    wire t1, t2, t3, t4, t5, t6, t7, t8;

    DFF2rx instance1(.D(data_in), .clk(clk), .Q(t1));
    DFF2rx instance2(.D(t1),.clk(clk), .Q(t2));
    DFF2rx instance3(.D(t2),.clk(clk), .Q(t3));
    DFF2rx instance4(.D(t3),.clk(clk), .Q(t4));
    DFF2rx instance5(.D(t4),.clk(clk), .Q(t5));
    DFF2rx instance6(.D(t5),.clk(clk), .Q(t6));
    DFF2rx instance7(.D(t6),.clk(clk), .Q(t7));
    DFF2rx instance8(.D(t7),.clk(clk), .Q(t8));

    assign h = t2; 
    assign g = t3; 
    assign f = t4; 
    assign e = t5;
    assign d = t6; 
    assign c = t7; 
    assign b = t8; 
    assign a = t1;
    
endmodule

baud_gen.v
module BaudGen(
    input clk,
    output reg tick
);

    reg [4:0] count = 0;                       //cuz 20 requiers 5 bit in binary 

    always @(posedge clk) 
    begin                   
        if(count >= 19)                        // 20 clock cycles per baud cuz easy for simmulation purpose
            begin
                count <= 0;
                tick <= 1;
            end 
        else 
            begin
                count <= count + 1;
                tick <= 0;
            end
    end

endmodule

FSMRX.v
module FSMRX(
    input clk,
    input rx,
    output reg Done,
    output [7:0] dataout,
    output tick
);
    
    wire a, b, c, d, e, f, g, h;
    assign dataout = {h, g, f, e, d, c, b, a };  // LSB first

    reg [2:0] state = 0;
    reg [2:0] bit_cnt = 0;

    parameter IDLE = 0, START = 1, DATA = 2, STOP = 3, DONE_STATE = 4;

    BaudGen baudgen(.clk(clk), .tick(tick));
    SIPO sipo(.clk(tick), .data_in(rx), .a(a), .b(b), .c(c), .d(d), .e(e), .f(f), .g(g), .h(h));

    always @(posedge clk) 
        begin
            case (state)
                IDLE: 
                    begin
                        Done <= 0;
                        bit_cnt <= 0;
                        if (rx == 0) 
                            begin
                                state <= START;
                            end
                    end

                START: 
                    begin
                        if (tick) 
                            begin 
                                state <= DATA;  // start bit sampled
                            end
                    end

                DATA: 
                    begin
                        if (tick) 
                            begin
                                if (bit_cnt == 7) 
                                    begin
                                        state <= STOP;
                                    end
                                else 
                                    begin
                                        bit_cnt <= bit_cnt + 1;
                                    end     
                            end
                    end

                STOP: 
                    begin
                        if (tick) 
                            begin
                                state <= DONE_STATE;
                            end
                    end

                DONE_STATE: 
                    begin
                        Done <= 1;
                        state <= IDLE;
                    end
            endcase
        end
endmodule

FSMRX_tb.v
`timescale 1ns / 1ps

module FSMRX_tb;

    reg clk = 0;
    reg rx = 1;
    wire Done;
    wire [7:0] dataout;
    wire tick;

    FSMRX uut (
        .clk(clk),
        .rx(rx),
        .Done(Done),
        .dataout(dataout),
        .tick(tick)
    );

    // Clock generation
    always #1 clk = ~clk;  // 500MHz for 20ns baud tick

    task send_byte;
        input [7:0] data;
        integer i;
        begin
            // Start bit
            rx = 0; repeat (20) @(posedge clk);
            // Data bits (LSB first)
            for (i = 0; i < 8; i = i + 1) begin
                rx = data[i];
                repeat (20) @(posedge clk);
            end
            // Stop bit
            rx = 1; repeat (20) @(posedge clk);
        end
    endtask

    initial begin
        $dumpfile("FSMRX_tb.vcd");
        $dumpvars(0, FSMRX_tb);

        $display("Starting FSMRX test...");

        @(posedge clk);
        $display("Sending first byte: 10010101");
        send_byte(8'b10010101);
        wait (Done); #5;
        $display("Received: %b", dataout);

        

        $display("FSMRX test complete.");
        $finish;
    end
endmodule

FSMRX_tb.vcd
$date
	Sun Jul 13 11:26:48 2025
$end
$version
	Icarus Verilog
$end
$timescale
	1ps
$end
$scope module FSMRX_tb $end
$var wire 1 ! tick $end
$var wire 8 " dataout [7:0] $end
$var wire 1 # Done $end
$var reg 1 $ clk $end
$var reg 1 % rx $end
$scope module uut $end
$var wire 1 $ clk $end
$var wire 1 % rx $end
$var wire 1 ! tick $end
$var wire 1 & h $end
$var wire 1 ' g $end
$var wire 1 ( f $end
$var wire 1 ) e $end
$var wire 8 * dataout [7:0] $end
$var wire 1 + d $end
$var wire 1 , c $end
$var wire 1 - b $end
$var wire 1 . a $end
$var parameter 32 / DATA $end
$var parameter 32 0 DONE_STATE $end
$var parameter 32 1 IDLE $end
$var parameter 32 2 START $end
$var parameter 32 3 STOP $end
$var reg 1 # Done $end
$var reg 3 4 bit_cnt [2:0] $end
$var reg 3 5 state [2:0] $end
$scope module baudgen $end
$var wire 1 $ clk $end
$var reg 5 6 count [4:0] $end
$var reg 1 ! tick $end
$upscope $end
$scope module sipo $end
$var wire 1 . a $end
$var wire 1 - b $end
$var wire 1 , c $end
$var wire 1 ! clk $end
$var wire 1 + d $end
$var wire 1 % data_in $end
$var wire 1 ) e $end
$var wire 1 ( f $end
$var wire 1 ' g $end
$var wire 1 & h $end
$var wire 1 7 t8 $end
$var wire 1 8 t7 $end
$var wire 1 9 t6 $end
$var wire 1 : t5 $end
$var wire 1 ; t4 $end
$var wire 1 < t3 $end
$var wire 1 = t2 $end
$var wire 1 > t1 $end
$scope module instance1 $end
$var wire 1 % D $end
$var wire 1 ! clk $end
$var reg 1 > Q $end
$upscope $end
$scope module instance2 $end
$var wire 1 > D $end
$var wire 1 ! clk $end
$var reg 1 = Q $end
$upscope $end
$scope module instance3 $end
$var wire 1 = D $end
$var wire 1 ! clk $end
$var reg 1 < Q $end
$upscope $end
$scope module instance4 $end
$var wire 1 < D $end
$var wire 1 ! clk $end
$var reg 1 ; Q $end
$upscope $end
$scope module instance5 $end
$var wire 1 ; D $end
$var wire 1 ! clk $end
$var reg 1 : Q $end
$upscope $end
$scope module instance6 $end
$var wire 1 : D $end
$var wire 1 ! clk $end
$var reg 1 9 Q $end
$upscope $end
$scope module instance7 $end
$var wire 1 9 D $end
$var wire 1 ! clk $end
$var reg 1 8 Q $end
$upscope $end
$scope module instance8 $end
$var wire 1 8 D $end
$var wire 1 ! clk $end
$var reg 1 7 Q $end
$upscope $end
$upscope $end
$upscope $end
$scope task send_byte $end
$var reg 8 ? data [7:0] $end
$var integer 32 @ i [31:0] $end
$upscope $end
$upscope $end
$enddefinitions $end
$comment Show the parameter values. $end
$dumpall
b11 3
b1 2
b0 1
b100 0
b10 /
$end
#0
$dumpvars
bx @
bx ?
x>
x=
x<
x;
x:
x9
x8
x7
b0 6
b0 5
b0 4
x.
x-
x,
x+
bx *
x)
x(
x'
x&
1%
0$
x#
bx "
x!
$end
#1000
0!
b1 6
0#
0%
b10010101 ?
1$
#2000
0$
#3000
b1 5
b10 6
1$
#4000
0$
#5000
b11 6
1$
#6000
0$
#7000
b100 6
1$
#8000
0$
#9000
b101 6
1$
#10000
0$
#11000
b110 6
1$
#12000
0$
#13000
b111 6
1$
#14000
0$
#15000
b1000 6
1$
#16000
0$
#17000
b1001 6
1$
#18000
0$
#19000
b1010 6
1$
#20000
0$
#21000
b1011 6
1$
#22000
0$
#23000
b1100 6
1$
#24000
0$
#25000
b1101 6
1$
#26000
0$
#27000
b1110 6
1$
#28000
0$
#29000
b1111 6
1$
#30000
0$
#31000
b10000 6
1$
#32000
0$
#33000
b10001 6
1$
#34000
0$
#35000
b10010 6
1$
#36000
0$
#37000
b10011 6
1$
#38000
0$
#39000
bx0 "
bx0 *
0.
0>
1!
b0 6
1$
#40000
0$
#41000
0!
b1 6
b10 5
1%
b0 @
1$
#42000
0$
#43000
b10 6
1$
#44000
0$
#45000
b11 6
1$
#46000
0$
#47000
b100 6
1$
#48000
0$
#49000
b101 6
1$
#50000
0$
#51000
b110 6
1$
#52000
0$
#53000
b111 6
1$
#54000
0$
#55000
b1000 6
1$
#56000
0$
#57000
b1001 6
1$
#58000
0$
#59000
b1010 6
1$
#60000
0$
#61000
b1011 6
1$
#62000
0$
#63000
b1100 6
1$
#64000
0$
#65000
b1101 6
1$
#66000
0$
#67000
b1110 6
1$
#68000
0$
#69000
b1111 6
1$
#70000
0$
#71000
b10000 6
1$
#72000
0$
#73000
b10001 6
1$
#74000
0$
#75000
b10010 6
1$
#76000
0$
#77000
b10011 6
1$
#78000
0$
#79000
0&
0=
b0xxxxxx1 "
b0xxxxxx1 *
1.
1>
1!
b0 6
1$
#80000
0$
#81000
0!
b1 6
b1 4
0%
b1 @
1$
#82000
0$
#83000
b10 6
1$
#84000
0$
#85000
b11 6
1$
#86000
0$
#87000
b100 6
1$
#88000
0$
#89000
b101 6
1$
#90000
0$
#91000
b110 6
1$
#92000
0$
#93000
b111 6
1$
#94000
0$
#95000
b1000 6
1$
#96000
0$
#97000
b1001 6
1$
#98000
0$
#99000
b1010 6
1$
#100000
0$
#101000
b1011 6
1$
#102000
0$
#103000
b1100 6
1$
#104000
0$
#105000
b1101 6
1$
#106000
0$
#107000
b1110 6
1$
#108000
0$
#109000
b1111 6
1$
#110000
0$
#111000
b10000 6
1$
#112000
0$
#113000
b10001 6
1$
#114000
0$
#115000
b10010 6
1$
#116000
0$
#117000
b10011 6
1$
#118000
0$
#119000
0.
0>
1&
1=
b10xxxxx0 "
b10xxxxx0 *
0'
0<
1!
b0 6
1$
#120000
0$
#121000
0!
b1 6
b10 4
1%
b10 @
1$
#122000
0$
#123000
b10 6
1$
#124000
0$
#125000
b11 6
1$
#126000
0$
#127000
b100 6
1$
#128000
0$
#129000
b101 6
1$
#130000
0$
#131000
b110 6
1$
#132000
0$
#133000
b111 6
1$
#134000
0$
#135000
b1000 6
1$
#136000
0$
#137000
b1001 6
1$
#138000
0$
#139000
b1010 6
1$
#140000
0$
#141000
b1011 6
1$
#142000
0$
#143000
b1100 6
1$
#144000
0$
#145000
b1101 6
1$
#146000
0$
#147000
b1110 6
1$
#148000
0$
#149000
b1111 6
1$
#150000
0$
#151000
b10000 6
1$
#152000
0$
#153000
b10001 6
1$
#154000
0$
#155000
b10010 6
1$
#156000
0$
#157000
b10011 6
1$
#158000
0$
#159000
0(
0;
1'
1<
0&
0=
b10xxxx1 "
b10xxxx1 *
1.
1>
1!
b0 6
1$
#160000
0$
#161000
0!
b1 6
b11 4
0%
b11 @
1$
#162000
0$
#163000
b10 6
1$
#164000
0$
#165000
b11 6
1$
#166000
0$
#167000
b100 6
1$
#168000
0$
#169000
b101 6
1$
#170000
0$
#171000
b110 6
1$
#172000
0$
#173000
b111 6
1$
#174000
0$
#175000
b1000 6
1$
#176000
0$
#177000
b1001 6
1$
#178000
0$
#179000
b1010 6
1$
#180000
0$
#181000
b1011 6
1$
#182000
0$
#183000
b1100 6
1$
#184000
0$
#185000
b1101 6
1$
#186000
0$
#187000
b1110 6
1$
#188000
0$
#189000
b1111 6
1$
#190000
0$
#191000
b10000 6
1$
#192000
0$
#193000
b10001 6
1$
#194000
0$
#195000
b10010 6
1$
#196000
0$
#197000
b10011 6
1$
#198000
0$
#199000
0.
0>
1&
1=
0'
0<
1(
1;
b1010xxx0 "
b1010xxx0 *
0)
0:
1!
b0 6
1$
#200000
0$
#201000
0!
b1 6
b100 4
1%
b100 @
1$
#202000
0$
#203000
b10 6
1$
#204000
0$
#205000
b11 6
1$
#206000
0$
#207000
b100 6
1$
#208000
0$
#209000
b101 6
1$
#210000
0$
#211000
b110 6
1$
#212000
0$
#213000
b111 6
1$
#214000
0$
#215000
b1000 6
1$
#216000
0$
#217000
b1001 6
1$
#218000
0$
#219000
b1010 6
1$
#220000
0$
#221000
b1011 6
1$
#222000
0$
#223000
b1100 6
1$
#224000
0$
#225000
b1101 6
1$
#226000
0$
#227000
b1110 6
1$
#228000
0$
#229000
b1111 6
1$
#230000
0$
#231000
b10000 6
1$
#232000
0$
#233000
b10001 6
1$
#234000
0$
#235000
b10010 6
1$
#236000
0$
#237000
b10011 6
1$
#238000
0$
#239000
0+
09
1)
1:
0(
0;
1'
1<
0&
0=
b1010xx1 "
b1010xx1 *
1.
1>
1!
b0 6
1$
#240000
0$
#241000
0!
b1 6
b101 4
0%
b101 @
1$
#242000
0$
#243000
b10 6
1$
#244000
0$
#245000
b11 6
1$
#246000
0$
#247000
b100 6
1$
#248000
0$
#249000
b101 6
1$
#250000
0$
#251000
b110 6
1$
#252000
0$
#253000
b111 6
1$
#254000
0$
#255000
b1000 6
1$
#256000
0$
#257000
b1001 6
1$
#258000
0$
#259000
b1010 6
1$
#260000
0$
#261000
b1011 6
1$
#262000
0$
#263000
b1100 6
1$
#264000
0$
#265000
b1101 6
1$
#266000
0$
#267000
b1110 6
1$
#268000
0$
#269000
b1111 6
1$
#270000
0$
#271000
b10000 6
1$
#272000
0$
#273000
b10001 6
1$
#274000
0$
#275000
b10010 6
1$
#276000
0$
#277000
b10011 6
1$
#278000
0$
#279000
0.
0>
1&
1=
0'
0<
1(
1;
0)
0:
1+
19
b101010x0 "
b101010x0 *
0,
08
1!
b0 6
1$
#280000
0$
#281000
0!
b1 6
b110 4
b110 @
1$
#282000
0$
#283000
b10 6
1$
#284000
0$
#285000
b11 6
1$
#286000
0$
#287000
b100 6
1$
#288000
0$
#289000
b101 6
1$
#290000
0$
#291000
b110 6
1$
#292000
0$
#293000
b111 6
1$
#294000
0$
#295000
b1000 6
1$
#296000
0$
#297000
b1001 6
1$
#298000
0$
#299000
b1010 6
1$
#300000
0$
#301000
b1011 6
1$
#302000
0$
#303000
b1100 6
1$
#304000
0$
#305000
b1101 6
1$
#306000
0$
#307000
b1110 6
1$
#308000
0$
#309000
b1111 6
1$
#310000
0$
#311000
b10000 6
1$
#312000
0$
#313000
b10001 6
1$
#314000
0$
#315000
b10010 6
1$
#316000
0$
#317000
b10011 6
1$
#318000
0$
#319000
0-
07
1,
18
0+
09
1)
1:
0(
0;
1'
1<
b1010100 "
b1010100 *
0&
0=
1!
b0 6
1$
#320000
0$
#321000
0!
b1 6
b111 4
1%
b111 @
1$
#322000
0$
#323000
b10 6
1$
#324000
0$
#325000
b11 6
1$
#326000
0$
#327000
b100 6
1$
#328000
0$
#329000
b101 6
1$
#330000
0$
#331000
b110 6
1$
#332000
0$
#333000
b111 6
1$
#334000
0$
#335000
b1000 6
1$
#336000
0$
#337000
b1001 6
1$
#338000
0$
#339000
b1010 6
1$
#340000
0$
#341000
b1011 6
1$
#342000
0$
#343000
b1100 6
1$
#344000
0$
#345000
b1101 6
1$
#346000
0$
#347000
b1110 6
1$
#348000
0$
#349000
b1111 6
1$
#350000
0$
#351000
b10000 6
1$
#352000
0$
#353000
b10001 6
1$
#354000
0$
#355000
b10010 6
1$
#356000
0$
#357000
b10011 6
1$
#358000
0$
#359000
1.
1>
0'
0<
1(
1;
0)
0:
1+
19
0,
08
b101011 "
b101011 *
1-
17
1!
b0 6
1$
#360000
0$
#361000
0!
b1 6
b11 5
b1000 @
1$
#362000
0$
#363000
b10 6
1$
#364000
0$
#365000
b11 6
1$
#366000
0$
#367000
b100 6
1$
#368000
0$
#369000
b101 6
1$
#370000
0$
#371000
b110 6
1$
#372000
0$
#373000
b111 6
1$
#374000
0$
#375000
b1000 6
1$
#376000
0$
#377000
b1001 6
1$
#378000
0$
#379000
b1010 6
1$
#380000
0$
#381000
b1011 6
1$
#382000
0$
#383000
b1100 6
1$
#384000
0$
#385000
b1101 6
1$
#386000
0$
#387000
b1110 6
1$
#388000
0$
#389000
b1111 6
1$
#390000
0$
#391000
b10000 6
1$
#392000
0$
#393000
b10001 6
1$
#394000
0$
#395000
b10010 6
1$
#396000
0$
#397000
b10011 6
1$
#398000
0$
#399000
0-
07
1,
18
0+
09
1)
1:
0(
0;
b10010101 "
b10010101 *
1&
1=
1!
b0 6
1$
#400000
0$
#401000
0!
b1 6
b100 5
1$
#402000
0$
#403000
b0 5
1#
b10 6
1$
#404000
0$
#405000
b11 6
b0 4
0#
1$
#406000
0$
#407000
b100 6
1$
