uart_tx.v
module PISO(
    input a, b, c, d, e, f, g, h,
    input clk, load, tx,
    output reg t20
);
    reg [7:0] data;
    reg [2:0] count = 0;

    always @(posedge clk) begin
        if (load) begin
            data <= {a, b, c, d, e, f, g, h};       // at load =1 data in parallely
            count <= 0;
        end else if (~tx) begin
            t20 <= data[count];                     // data transmission from lsb first to msb
            count <= count + 1;
        end
        else 
         begin
            t20 <= 1'b1;  // therefore at tx==1 output ==x cuz it is stop bit
        end
    end
endmodule









// module PISO(
//     input load,a,b,c,d,e,f,g,h,clk,tx,
//     output t20
//     );
    
// wire t1,t2,t3,t6,t7,t8,t9,t10,t11,t12,t13,t14,t15,t16,t17,t18,t19;
// assign t1= ~load;
// assign t2= load;

// assign t3= clk & ~tx;

// DFF1tx instance1(.D(a), .clk(t3), .t7(t7), .in1(t2), .in2(t1), .in3(b) );
// DFF1tx instance2(.D(t7), .clk(t3), .t7(t8), .in1(t2), .in2(t1), .in3(c));
// DFF1tx instance3(.D(t8), .clk(t3), .t7(t10), .in1(t2), .in2(t1), .in3(d));
// DFF1tx instance4(.D(t10), .clk(t3), .t7(t12), .in1(t2), .in2(t1), .in3(e));
// DFF1tx instance5(.D(t12), .clk(t3), .t7(t14), .in1(t2), .in2(t1), .in3(f));
// DFF1tx instance6(.D(t14), .clk(t3), .t7(t16), .in1(t2), .in2(t1), .in3(g));
// DFF1tx instance7(.D(t16), .clk(t3), .t7(t18), .in1(t2), .in2(t1), .in3(h));
// DFF1tx instance8(.D(t18), .clk(t3), .t7(t20), .in1(1'b1), .in2(1'b0), .in3(1'b0));


// endmodule

baud_gen.v
module BaudGen(
    input clk,
    output reg tick
);

    reg [4:0] count = 0;                       //cuz 20 requiers 5 bit in binary 

    always @(posedge clk) 
    begin                   
        if(count >= 19)                        // 20 clock cycles per baud cuz easy for simmulation purpose
            begin
                count <= 0;
                tick <= 1;
            end 
        else 
            begin
                count <= count + 1;
                tick <= 0;
            end
    end

endmodule

FSMTX.v
module FSMTX(
    input clk,
    input reset,                        //for idle state to stay at idle
    input [7:0] datain,
    output Done,
    output wire x,                      //  x a wire now it can be reset to x previously it was reg that's why my ,ine 26 was not able to assign x==x it has to be continous for that
    output tick                         // Baud tick 
);

    reg tx, load;
    reg [3:0] bit_cnt;
    reg [2:0] state, nstate;

    parameter IDLE = 0, LOAD = 1, DATA = 2, STOP = 3, DONE = 4, CLEANUP = 5;

    // Internal wire to receive output from PISO
    wire t20_internal;                                  //cuz we can assign wire to x after transmission is stoped


    // instanciation of transmitter and baud gen
    BaudGen instance1(.clk(clk), .tick(tick));
    PISO instance2(.a(datain[7]), .b(datain[6]), .c(datain[5]), .d(datain[4]), .e(datain[3]), .f(datain[2]), .g(datain[1]), .h(datain[0]), .clk(tick), .load(load), .tx(tx), .t20(t20_internal));
    

    // Assign x = 'x' when tx = 1 (idle); otherwise pass data bit
    assign x = (tx == 1'b1) ? 1'b1 : t20_internal;      //this stops data transmission after the stop bit

    // Next state logic acc to stat diagram
    always @(*) begin
        case (state)
            IDLE:nstate = LOAD;
            LOAD:nstate = DATA;
            DATA:nstate = (bit_cnt == 8) ? STOP : DATA;
            STOP:nstate = DONE;
            DONE:nstate = CLEANUP;
            CLEANUP: nstate = IDLE;                     //just stops data transmission after the stop bit that's why cleanup state is used
            default: nstate = IDLE;
        endcase
    end

    // conditions for the state to change there state
    always @(posedge tick or posedge reset) 
    begin
        if (reset) 
            begin                                       //reset==1 is used for idle state to stay at ideal state
                state <= IDLE;
                tx <= 1;
                load <= 0;
                bit_cnt <= 0;
            end 
        else 
            begin
                state <= nstate;
                case (state)
                    IDLE: 
                        begin
                            tx <= 1;
                            load <= 0;                  //parallel data loads into register
                            bit_cnt <= 0;
                        end
                    
                    LOAD: 
                        begin
                            tx <= 1;                    //still data transmission not started
                            load <= 1;                  //start shifting data serially
                        end

                    DATA: 
                        begin
                            tx <= 0;                    // at data stage data transmission starts
                            load <= 0;
                            bit_cnt <= bit_cnt + 1;     //data will transmit til bitcnt==8 bits then next stage
                        end

                    STOP: 
                        begin
                            tx <= 1;                    // tx==1 so data transmission stops
                        end

                    DONE: 
                        begin
                            tx <= 1;                    //same here
                        end

                    CLEANUP: 
                        begin                           //just to stop further transmission of wrong bits
                            tx <= 1;
                            load <= 0;                  
                            bit_cnt <= 0;               // bit count reset
                        end
                endcase
            end
    end

    assign Done = (state == DONE);                      // will print outpt ==1 when transmisson is done 

endmodule

FSMTX_tb.v
// module testb ;
// reg t1;
// wire t3;
// reg t2;
//  DFF1 instance1(.D(t1), .clk(t2), .Q(t3));
//  initial begin
//     t2 = 0;
//     #50 $finish;
//  end
//  always #5 t2=~t2;
//  initial
//  begin
//     $monitor("%t %d %d", $time , t1 , t3);
//     #2 t1= 1'b0;
//     #7 t1= 1'b1;
//  end
// endmodule

`timescale 1ns / 1ps

module FSMTX_tb;

    reg clk, reset;
    reg [7:0] datain;
    wire Done, x, tick;

    FSMTX uut (
        .clk(clk),
        .reset(reset),
        .datain(datain),
        .Done(Done),
        .x(x),
        .tick(tick)
    );

    // Clock generation
    initial begin
        clk = 0;
        forever #20 clk = ~clk; // 50MHz clock
    end

    integer tick_count = 0;
    integer tx_count = 0;

    initial begin
        $display("Time\tTick\tX\tbit_cnt\tLoad\tDone\tState");
        $dumpfile("FSMTX_tb.vcd");
        $dumpvars(0, FSMTX_tb);

        $display("Starting FSMTX transmission test...");
        datain = 8'b10110011;
        reset = 1; #20; reset = 0;
        $display("Transmission Started for byte: %b", datain);
        $display("Tick\tX\tDone\tTx");

        forever begin
            @(posedge tick);
            tick_count = tick_count + 1;
           $display("%2d\t%s\t%b\t%b", tick_count, (x === 1'bx) ? "x" : (x ? "1" : "0"), Done, uut.tx);


            if (Done) begin
                tx_count = tx_count + 1;
                $display("Transmission %0d Done!\n", tx_count);
                if (tx_count == 2) begin
                    $display(" Simulation complete after 2 transmissions.");
                    $finish;
                end
                #40;
                datain = (tx_count == 1) ? 8'b11001100 : 8'b00000000; // Only use 2 values
                $display("Starting new transmission for byte: %b", datain);
                reset = 1; #20; reset = 0;
                tick_count = 0;
            end
        end
    end

endmodule

FSMTX_tb.vcd
$date
	Tue Jul 01 21:08:45 2025
$end
$version
	Icarus Verilog
$end
$timescale
	1ps
$end
$scope module FSMTX_tb $end
$var wire 1 ! x $end
$var wire 1 " tick $end
$var wire 1 # Done $end
$var reg 1 $ clk $end
$var reg 8 % datain [7:0] $end
$var reg 1 & reset $end
$var integer 32 ' tick_count [31:0] $end
$var integer 32 ( tx_count [31:0] $end
$scope module uut $end
$var wire 1 $ clk $end
$var wire 8 ) datain [7:0] $end
$var wire 1 & reset $end
$var wire 1 ! x $end
$var wire 1 " tick $end
$var wire 1 * t20_internal $end
$var wire 1 # Done $end
$var parameter 32 + CLEANUP $end
$var parameter 32 , DATA $end
$var parameter 32 - DONE $end
$var parameter 32 . IDLE $end
$var parameter 32 / LOAD $end
$var parameter 32 0 STOP $end
$var reg 4 1 bit_cnt [3:0] $end
$var reg 1 2 load $end
$var reg 3 3 nstate [2:0] $end
$var reg 3 4 state [2:0] $end
$var reg 1 5 tx $end
$scope module instance1 $end
$var wire 1 $ clk $end
$var reg 5 6 count [4:0] $end
$var reg 1 " tick $end
$upscope $end
$scope module instance2 $end
$var wire 1 7 a $end
$var wire 1 8 b $end
$var wire 1 9 c $end
$var wire 1 " clk $end
$var wire 1 : d $end
$var wire 1 ; e $end
$var wire 1 < f $end
$var wire 1 = g $end
$var wire 1 > h $end
$var wire 1 2 load $end
$var wire 1 5 tx $end
$var reg 3 ? count [2:0] $end
$var reg 8 @ data [7:0] $end
$var reg 1 * t20 $end
$upscope $end
$upscope $end
$upscope $end
$enddefinitions $end
$comment Show the parameter values. $end
$dumpall
b11 0
b1 /
b0 .
b100 -
b10 ,
b101 +
$end
#0
$dumpvars
bx @
b0 ?
1>
1=
0<
0;
1:
19
08
17
b0 6
15
b0 4
b1 3
02
b0 1
x*
b10110011 )
b0 (
b0 '
1&
b10110011 %
0$
0#
x"
1!
$end
#20000
0"
b1 6
0&
1$
#40000
0$
#60000
b10 6
1$
#80000
0$
#100000
b11 6
1$
#120000
0$
#140000
b100 6
1$
#160000
0$
#180000
b101 6
1$
#200000
0$
#220000
b110 6
1$
#240000
0$
#260000
b111 6
1$
#280000
0$
#300000
b1000 6
1$
#320000
0$
#340000
b1001 6
1$
#360000
0$
#380000
b1010 6
1$
#400000
0$
#420000
b1011 6
1$
#440000
0$
#460000
b1100 6
1$
#480000
0$
#500000
b1101 6
1$
#520000
0$
#540000
b1110 6
1$
#560000
0$
#580000
b1111 6
1$
#600000
0$
#620000
b10000 6
1$
#640000
0$
#660000
b10001 6
1$
#680000
0$
#700000
b10010 6
1$
#720000
0$
#740000
b10011 6
1$
#760000
0$
#780000
b10 3
1*
b1 4
b1 '
1"
b0 6
1$
#800000
0$
#820000
0"
b1 6
1$
#840000
0$
#860000
b10 6
1$
#880000
0$
#900000
b11 6
1$
#920000
0$
#940000
b100 6
1$
#960000
0$
#980000
b101 6
1$
#1000000
0$
#1020000
b110 6
1$
#1040000
0$
#1060000
b111 6
1$
#1080000
0$
#1100000
b1000 6
1$
#1120000
0$
#1140000
b1001 6
1$
#1160000
0$
#1180000
b1010 6
1$
#1200000
0$
#1220000
b1011 6
1$
#1240000
0$
#1260000
b1100 6
1$
#1280000
0$
#1300000
b1101 6
1$
#1320000
0$
#1340000
b1110 6
1$
#1360000
0$
#1380000
b1111 6
1$
#1400000
0$
#1420000
b10000 6
1$
#1440000
0$
#1460000
b10001 6
1$
#1480000
0$
#1500000
b10010 6
1$
#1520000
0$
#1540000
b10011 6
1$
#1560000
0$
#1580000
12
b10 4
b10 '
1"
b0 6
1$
#1600000
0$
#1620000
0"
b1 6
1$
#1640000
0$
#1660000
b10 6
1$
#1680000
0$
#1700000
b11 6
1$
#1720000
0$
#1740000
b100 6
1$
#1760000
0$
#1780000
b101 6
1$
#1800000
0$
#1820000
b110 6
1$
#1840000
0$
#1860000
b111 6
1$
#1880000
0$
#1900000
b1000 6
1$
#1920000
0$
#1940000
b1001 6
1$
#1960000
0$
#1980000
b1010 6
1$
#2000000
0$
#2020000
b1011 6
1$
#2040000
0$
#2060000
b1100 6
1$
#2080000
0$
#2100000
b1101 6
1$
#2120000
0$
#2140000
b1110 6
1$
#2160000
0$
#2180000
b1111 6
1$
#2200000
0$
#2220000
b10000 6
1$
#2240000
0$
#2260000
b10001 6
1$
#2280000
0$
#2300000
b10010 6
1$
#2320000
0$
#2340000
b10011 6
1$
#2360000
0$
#2380000
b10110011 @
b1 1
02
05
b11 '
1"
b0 6
1$
#2400000
0$
#2420000
0"
b1 6
1$
#2440000
0$
#2460000
b10 6
1$
#2480000
0$
#2500000
b11 6
1$
#2520000
0$
#2540000
b100 6
1$
#2560000
0$
#2580000
b101 6
1$
#2600000
0$
#2620000
b110 6
1$
#2640000
0$
#2660000
b111 6
1$
#2680000
0$
#2700000
b1000 6
1$
#2720000
0$
#2740000
b1001 6
1$
#2760000
0$
#2780000
b1010 6
1$
#2800000
0$
#2820000
b1011 6
1$
#2840000
0$
#2860000
b1100 6
1$
#2880000
0$
#2900000
b1101 6
1$
#2920000
0$
#2940000
b1110 6
1$
#2960000
0$
#2980000
b1111 6
1$
#3000000
0$
#3020000
b10000 6
1$
#3040000
0$
#3060000
b10001 6
1$
#3080000
0$
#3100000
b10010 6
1$
#3120000
0$
#3140000
b10011 6
1$
#3160000
0$
#3180000
b1 ?
b10 1
b100 '
1"
b0 6
1$
#3200000
0$
#3220000
0"
b1 6
1$
#3240000
0$
#3260000
b10 6
1$
#3280000
0$
#3300000
b11 6
1$
#3320000
0$
#3340000
b100 6
1$
#3360000
0$
#3380000
b101 6
1$
#3400000
0$
#3420000
b110 6
1$
#3440000
0$
#3460000
b111 6
1$
#3480000
0$
#3500000
b1000 6
1$
#3520000
0$
#3540000
b1001 6
1$
#3560000
0$
#3580000
b1010 6
1$
#3600000
0$
#3620000
b1011 6
1$
#3640000
0$
#3660000
b1100 6
1$
#3680000
0$
#3700000
b1101 6
1$
#3720000
0$
#3740000
b1110 6
1$
#3760000
0$
#3780000
b1111 6
1$
#3800000
0$
#3820000
b10000 6
1$
#3840000
0$
#3860000
b10001 6
1$
#3880000
0$
#3900000
b10010 6
1$
#3920000
0$
#3940000
b10011 6
1$
#3960000
0$
#3980000
b10 ?
b11 1
b101 '
1"
b0 6
1$
#4000000
0$
#4020000
0"
b1 6
1$
#4040000
0$
#4060000
b10 6
1$
#4080000
0$
#4100000
b11 6
1$
#4120000
0$
#4140000
b100 6
1$
#4160000
0$
#4180000
b101 6
1$
#4200000
0$
#4220000
b110 6
1$
#4240000
0$
#4260000
b111 6
1$
#4280000
0$
#4300000
b1000 6
1$
#4320000
0$
#4340000
b1001 6
1$
#4360000
0$
#4380000
b1010 6
1$
#4400000
0$
#4420000
b1011 6
1$
#4440000
0$
#4460000
b1100 6
1$
#4480000
0$
#4500000
b1101 6
1$
#4520000
0$
#4540000
b1110 6
1$
#4560000
0$
#4580000
b1111 6
1$
#4600000
0$
#4620000
b10000 6
1$
#4640000
0$
#4660000
b10001 6
1$
#4680000
0$
#4700000
b10010 6
1$
#4720000
0$
#4740000
b10011 6
1$
#4760000
0$
#4780000
0!
b11 ?
0*
b100 1
b110 '
1"
b0 6
1$
#4800000
0$
#4820000
0"
b1 6
1$
#4840000
0$
#4860000
b10 6
1$
#4880000
0$
#4900000
b11 6
1$
#4920000
0$
#4940000
b100 6
1$
#4960000
0$
#4980000
b101 6
1$
#5000000
0$
#5020000
b110 6
1$
#5040000
0$
#5060000
b111 6
1$
#5080000
0$
#5100000
b1000 6
1$
#5120000
0$
#5140000
b1001 6
1$
#5160000
0$
#5180000
b1010 6
1$
#5200000
0$
#5220000
b1011 6
1$
#5240000
0$
#5260000
b1100 6
1$
#5280000
0$
#5300000
b1101 6
1$
#5320000
0$
#5340000
b1110 6
1$
#5360000
0$
#5380000
b1111 6
1$
#5400000
0$
#5420000
b10000 6
1$
#5440000
0$
#5460000
b10001 6
1$
#5480000
0$
#5500000
b10010 6
1$
#5520000
0$
#5540000
b10011 6
1$
#5560000
0$
#5580000
b100 ?
b101 1
b111 '
1"
b0 6
1$
#5600000
0$
#5620000
0"
b1 6
1$
#5640000
0$
#5660000
b10 6
1$
#5680000
0$
#5700000
b11 6
1$
#5720000
0$
#5740000
b100 6
1$
#5760000
0$
#5780000
b101 6
1$
#5800000
0$
#5820000
b110 6
1$
#5840000
0$
#5860000
b111 6
1$
#5880000
0$
#5900000
b1000 6
1$
#5920000
0$
#5940000
b1001 6
1$
#5960000
0$
#5980000
b1010 6
1$
#6000000
0$
#6020000
b1011 6
1$
#6040000
0$
#6060000
b1100 6
1$
#6080000
0$
#6100000
b1101 6
1$
#6120000
0$
#6140000
b1110 6
1$
#6160000
0$
#6180000
b1111 6
1$
#6200000
0$
#6220000
b10000 6
1$
#6240000
0$
#6260000
b10001 6
1$
#6280000
0$
#6300000
b10010 6
1$
#6320000
0$
#6340000
b10011 6
1$
#6360000
0$
#6380000
1!
b101 ?
1*
b110 1
b1000 '
1"
b0 6
1$
#6400000
0$
#6420000
0"
b1 6
1$
#6440000
0$
#6460000
b10 6
1$
#6480000
0$
#6500000
b11 6
1$
#6520000
0$
#6540000
b100 6
1$
#6560000
0$
#6580000
b101 6
1$
#6600000
0$
#6620000
b110 6
1$
#6640000
0$
#6660000
b111 6
1$
#6680000
0$
#6700000
b1000 6
1$
#6720000
0$
#6740000
b1001 6
1$
#6760000
0$
#6780000
b1010 6
1$
#6800000
0$
#6820000
b1011 6
1$
#6840000
0$
#6860000
b1100 6
1$
#6880000
0$
#6900000
b1101 6
1$
#6920000
0$
#6940000
b1110 6
1$
#6960000
0$
#6980000
b1111 6
1$
#7000000
0$
#7020000
b10000 6
1$
#7040000
0$
#7060000
b10001 6
1$
#7080000
0$
#7100000
b10010 6
1$
#7120000
0$
#7140000
b10011 6
1$
#7160000
0$
#7180000
b110 ?
b111 1
b1001 '
1"
b0 6
1$
#7200000
0$
#7220000
0"
b1 6
1$
#7240000
0$
#7260000
b10 6
1$
#7280000
0$
#7300000
b11 6
1$
#7320000
0$
#7340000
b100 6
1$
#7360000
0$
#7380000
b101 6
1$
#7400000
0$
#7420000
b110 6
1$
#7440000
0$
#7460000
b111 6
1$
#7480000
0$
#7500000
b1000 6
1$
#7520000
0$
#7540000
b1001 6
1$
#7560000
0$
#7580000
b1010 6
1$
#7600000
0$
#7620000
b1011 6
1$
#7640000
0$
#7660000
b1100 6
1$
#7680000
0$
#7700000
b1101 6
1$
#7720000
0$
#7740000
b1110 6
1$
#7760000
0$
#7780000
b1111 6
1$
#7800000
0$
#7820000
b10000 6
1$
#7840000
0$
#7860000
b10001 6
1$
#7880000
0$
#7900000
b10010 6
1$
#7920000
0$
#7940000
b10011 6
1$
#7960000
0$
#7980000
0!
b11 3
b111 ?
0*
b1000 1
b1010 '
1"
b0 6
1$
#8000000
0$
#8020000
0"
b1 6
1$
#8040000
0$
#8060000
b10 6
1$
#8080000
0$
#8100000
b11 6
1$
#8120000
0$
#8140000
b100 6
1$
#8160000
0$
#8180000
b101 6
1$
#8200000
0$
#8220000
b110 6
1$
#8240000
0$
#8260000
b111 6
1$
#8280000
0$
#8300000
b1000 6
1$
#8320000
0$
#8340000
b1001 6
1$
#8360000
0$
#8380000
b1010 6
1$
#8400000
0$
#8420000
b1011 6
1$
#8440000
0$
#8460000
b1100 6
1$
#8480000
0$
#8500000
b1101 6
1$
#8520000
0$
#8540000
b1110 6
1$
#8560000
0$
#8580000
b1111 6
1$
#8600000
0$
#8620000
b10000 6
1$
#8640000
0$
#8660000
b10001 6
1$
#8680000
0$
#8700000
b10010 6
1$
#8720000
0$
#8740000
b10011 6
1$
#8760000
0$
#8780000
1!
b100 3
b0 ?
1*
b1001 1
b11 4
b1011 '
1"
b0 6
1$
#8800000
0$
#8820000
0"
b1 6
1$
#8840000
0$
#8860000
b10 6
1$
#8880000
0$
#8900000
b11 6
1$
#8920000
0$
#8940000
b100 6
1$
#8960000
0$
#8980000
b101 6
1$
#9000000
0$
#9020000
b110 6
1$
#9040000
0$
#9060000
b111 6
1$
#9080000
0$
#9100000
b1000 6
1$
#9120000
0$
#9140000
b1001 6
1$
#9160000
0$
#9180000
b1010 6
1$
#9200000
0$
#9220000
b1011 6
1$
#9240000
0$
#9260000
b1100 6
1$
#9280000
0$
#9300000
b1101 6
1$
#9320000
0$
#9340000
b1110 6
1$
#9360000
0$
#9380000
b1111 6
1$
#9400000
0$
#9420000
b10000 6
1$
#9440000
0$
#9460000
b10001 6
1$
#9480000
0$
#9500000
b10010 6
1$
#9520000
0$
#9540000
b10011 6
1$
#9560000
0$
#9580000
b101 3
b1 ?
15
1#
b100 4
b1100 '
1"
b0 6
1$
#9600000
0$
#9620000
0"
b1 6
1$
#9640000
0$
#9660000
b10 6
1$
#9680000
0$
#9700000
b11 6
1$
#9720000
0$
#9740000
b100 6
1$
#9760000
0$
#9780000
b101 6
1$
#9800000
0$
#9820000
b110 6
1$
#9840000
0$
#9860000
b111 6
1$
#9880000
0$
#9900000
b1000 6
1$
#9920000
0$
#9940000
b1001 6
1$
#9960000
0$
#9980000
b1010 6
1$
#10000000
0$
#10020000
b1011 6
1$
#10040000
0$
#10060000
b1100 6
1$
#10080000
0$
#10100000
b1101 6
1$
#10120000
0$
#10140000
b1110 6
1$
#10160000
0$
#10180000
b1111 6
1$
#10200000
0$
#10220000
b10000 6
1$
#10240000
0$
#10260000
b10001 6
1$
#10280000
0$
#10300000
b10010 6
1$
#10320000
0$
#10340000
b10011 6
1$
#10360000
0$
#10380000
b0 3
0#
b101 4
b1 (
b1101 '
1"
b0 6
1$
#10400000
0$
#10420000
b1 3
0"
b1 6
b0 1
b0 4
18
09
0:
1;
1<
0=
0>
1$
1&
b11001100 %
b11001100 )
#10440000
0$
b0 '
0&
#10460000
b10 6
1$
#10480000
0$
#10500000
b11 6
1$
#10520000
0$
#10540000
b100 6
1$
#10560000
0$
#10580000
b101 6
1$
#10600000
0$
#10620000
b110 6
1$
#10640000
0$
#10660000
b111 6
1$
#10680000
0$
#10700000
b1000 6
1$
#10720000
0$
#10740000
b1001 6
1$
#10760000
0$
#10780000
b1010 6
1$
#10800000
0$
#10820000
b1011 6
1$
#10840000
0$
#10860000
b1100 6
1$
#10880000
0$
#10900000
b1101 6
1$
#10920000
0$
#10940000
b1110 6
1$
#10960000
0$
#10980000
b1111 6
1$
#11000000
0$
#11020000
b10000 6
1$
#11040000
0$
#11060000
b10001 6
1$
#11080000
0$
#11100000
b10010 6
1$
#11120000
0$
#11140000
b10011 6
1$
#11160000
0$
#11180000
b10 3
b1 4
b1 '
1"
b0 6
1$
#11200000
0$
#11220000
0"
b1 6
1$
#11240000
0$
#11260000
b10 6
1$
#11280000
0$
#11300000
b11 6
1$
#11320000
0$
#11340000
b100 6
1$
#11360000
0$
#11380000
b101 6
1$
#11400000
0$
#11420000
b110 6
1$
#11440000
0$
#11460000
b111 6
1$
#11480000
0$
#11500000
b1000 6
1$
#11520000
0$
#11540000
b1001 6
1$
#11560000
0$
#11580000
b1010 6
1$
#11600000
0$
#11620000
b1011 6
1$
#11640000
0$
#11660000
b1100 6
1$
#11680000
0$
#11700000
b1101 6
1$
#11720000
0$
#11740000
b1110 6
1$
#11760000
0$
#11780000
b1111 6
1$
#11800000
0$
#11820000
b10000 6
1$
#11840000
0$
#11860000
b10001 6
1$
#11880000
0$
#11900000
b10010 6
1$
#11920000
0$
#11940000
b10011 6
1$
#11960000
0$
#11980000
12
b10 4
b10 '
1"
b0 6
1$
#12000000
0$
#12020000
0"
b1 6
1$
#12040000
0$
#12060000
b10 6
1$
#12080000
0$
#12100000
b11 6
1$
#12120000
0$
#12140000
b100 6
1$
#12160000
0$
#12180000
b101 6
1$
#12200000
0$
#12220000
b110 6
1$
#12240000
0$
#12260000
b111 6
1$
#12280000
0$
#12300000
b1000 6
1$
#12320000
0$
#12340000
b1001 6
1$
#12360000
0$
#12380000
b1010 6
1$
#12400000
0$
#12420000
b1011 6
1$
#12440000
0$
#12460000
b1100 6
1$
#12480000
0$
#12500000
b1101 6
1$
#12520000
0$
#12540000
b1110 6
1$
#12560000
0$
#12580000
b1111 6
1$
#12600000
0$
#12620000
b10000 6
1$
#12640000
0$
#12660000
b10001 6
1$
#12680000
0$
#12700000
b10010 6
1$
#12720000
0$
#12740000
b10011 6
1$
#12760000
0$
#12780000
b0 ?
b11001100 @
b1 1
02
05
b11 '
1"
b0 6
1$
#12800000
0$
#12820000
0"
b1 6
1$
#12840000
0$
#12860000
b10 6
1$
#12880000
0$
#12900000
b11 6
1$
#12920000
0$
#12940000
b100 6
1$
#12960000
0$
#12980000
b101 6
1$
#13000000
0$
#13020000
b110 6
1$
#13040000
0$
#13060000
b111 6
1$
#13080000
0$
#13100000
b1000 6
1$
#13120000
0$
#13140000
b1001 6
1$
#13160000
0$
#13180000
b1010 6
1$
#13200000
0$
#13220000
b1011 6
1$
#13240000
0$
#13260000
b1100 6
1$
#13280000
0$
#13300000
b1101 6
1$
#13320000
0$
#13340000
b1110 6
1$
#13360000
0$
#13380000
b1111 6
1$
#13400000
0$
#13420000
b10000 6
1$
#13440000
0$
#13460000
b10001 6
1$
#13480000
0$
#13500000
b10010 6
1$
#13520000
0$
#13540000
b10011 6
1$
#13560000
0$
#13580000
0!
b1 ?
0*
b10 1
b100 '
1"
b0 6
1$
#13600000
0$
#13620000
0"
b1 6
1$
#13640000
0$
#13660000
b10 6
1$
#13680000
0$
#13700000
b11 6
1$
#13720000
0$
#13740000
b100 6
1$
#13760000
0$
#13780000
b101 6
1$
#13800000
0$
#13820000
b110 6
1$
#13840000
0$
#13860000
b111 6
1$
#13880000
0$
#13900000
b1000 6
1$
#13920000
0$
#13940000
b1001 6
1$
#13960000
0$
#13980000
b1010 6
1$
#14000000
0$
#14020000
b1011 6
1$
#14040000
0$
#14060000
b1100 6
1$
#14080000
0$
#14100000
b1101 6
1$
#14120000
0$
#14140000
b1110 6
1$
#14160000
0$
#14180000
b1111 6
1$
#14200000
0$
#14220000
b10000 6
1$
#14240000
0$
#14260000
b10001 6
1$
#14280000
0$
#14300000
b10010 6
1$
#14320000
0$
#14340000
b10011 6
1$
#14360000
0$
#14380000
b10 ?
b11 1
b101 '
1"
b0 6
1$
#14400000
0$
#14420000
0"
b1 6
1$
#14440000
0$
#14460000
b10 6
1$
#14480000
0$
#14500000
b11 6
1$
#14520000
0$
#14540000
b100 6
1$
#14560000
0$
#14580000
b101 6
1$
#14600000
0$
#14620000
b110 6
1$
#14640000
0$
#14660000
b111 6
1$
#14680000
0$
#14700000
b1000 6
1$
#14720000
0$
#14740000
b1001 6
1$
#14760000
0$
#14780000
b1010 6
1$
#14800000
0$
#14820000
b1011 6
1$
#14840000
0$
#14860000
b1100 6
1$
#14880000
0$
#14900000
b1101 6
1$
#14920000
0$
#14940000
b1110 6
1$
#14960000
0$
#14980000
b1111 6
1$
#15000000
0$
#15020000
b10000 6
1$
#15040000
0$
#15060000
b10001 6
1$
#15080000
0$
#15100000
b10010 6
1$
#15120000
0$
#15140000
b10011 6
1$
#15160000
0$
#15180000
1!
b11 ?
1*
b100 1
b110 '
1"
b0 6
1$
#15200000
0$
#15220000
0"
b1 6
1$
#15240000
0$
#15260000
b10 6
1$
#15280000
0$
#15300000
b11 6
1$
#15320000
0$
#15340000
b100 6
1$
#15360000
0$
#15380000
b101 6
1$
#15400000
0$
#15420000
b110 6
1$
#15440000
0$
#15460000
b111 6
1$
#15480000
0$
#15500000
b1000 6
1$
#15520000
0$
#15540000
b1001 6
1$
#15560000
0$
#15580000
b1010 6
1$
#15600000
0$
#15620000
b1011 6
1$
#15640000
0$
#15660000
b1100 6
1$
#15680000
0$
#15700000
b1101 6
1$
#15720000
0$
#15740000
b1110 6
1$
#15760000
0$
#15780000
b1111 6
1$
#15800000
0$
#15820000
b10000 6
1$
#15840000
0$
#15860000
b10001 6
1$
#15880000
0$
#15900000
b10010 6
1$
#15920000
0$
#15940000
b10011 6
1$
#15960000
0$
#15980000
b100 ?
b101 1
b111 '
1"
b0 6
1$
#16000000
0$
#16020000
0"
b1 6
1$
#16040000
0$
#16060000
b10 6
1$
#16080000
0$
#16100000
b11 6
1$
#16120000
0$
#16140000
b100 6
1$
#16160000
0$
#16180000
b101 6
1$
#16200000
0$
#16220000
b110 6
1$
#16240000
0$
#16260000
b111 6
1$
#16280000
0$
#16300000
b1000 6
1$
#16320000
0$
#16340000
b1001 6
1$
#16360000
0$
#16380000
b1010 6
1$
#16400000
0$
#16420000
b1011 6
1$
#16440000
0$
#16460000
b1100 6
1$
#16480000
0$
#16500000
b1101 6
1$
#16520000
0$
#16540000
b1110 6
1$
#16560000
0$
#16580000
b1111 6
1$
#16600000
0$
#16620000
b10000 6
1$
#16640000
0$
#16660000
b10001 6
1$
#16680000
0$
#16700000
b10010 6
1$
#16720000
0$
#16740000
b10011 6
1$
#16760000
0$
#16780000
0!
b101 ?
0*
b110 1
b1000 '
1"
b0 6
1$
#16800000
0$
#16820000
0"
b1 6
1$
#16840000
0$
#16860000
b10 6
1$
#16880000
0$
#16900000
b11 6
1$
#16920000
0$
#16940000
b100 6
1$
#16960000
0$
#16980000
b101 6
1$
#17000000
0$
#17020000
b110 6
1$
#17040000
0$
#17060000
b111 6
1$
#17080000
0$
#17100000
b1000 6
1$
#17120000
0$
#17140000
b1001 6
1$
#17160000
0$
#17180000
b1010 6
1$
#17200000
0$
#17220000
b1011 6
1$
#17240000
0$
#17260000
b1100 6
1$
#17280000
0$
#17300000
b1101 6
1$
#17320000
0$
#17340000
b1110 6
1$
#17360000
0$
#17380000
b1111 6
1$
#17400000
0$
#17420000
b10000 6
1$
#17440000
0$
#17460000
b10001 6
1$
#17480000
0$
#17500000
b10010 6
1$
#17520000
0$
#17540000
b10011 6
1$
#17560000
0$
#17580000
b110 ?
b111 1
b1001 '
1"
b0 6
1$
#17600000
0$
#17620000
0"
b1 6
1$
#17640000
0$
#17660000
b10 6
1$
#17680000
0$
#17700000
b11 6
1$
#17720000
0$
#17740000
b100 6
1$
#17760000
0$
#17780000
b101 6
1$
#17800000
0$
#17820000
b110 6
1$
#17840000
0$
#17860000
b111 6
1$
#17880000
0$
#17900000
b1000 6
1$
#17920000
0$
#17940000
b1001 6
1$
#17960000
0$
#17980000
b1010 6
1$
#18000000
0$
#18020000
b1011 6
1$
#18040000
0$
#18060000
b1100 6
1$
#18080000
0$
#18100000
b1101 6
1$
#18120000
0$
#18140000
b1110 6
1$
#18160000
0$
#18180000
b1111 6
1$
#18200000
0$
#18220000
b10000 6
1$
#18240000
0$
#18260000
b10001 6
1$
#18280000
0$
#18300000
b10010 6
1$
#18320000
0$
#18340000
b10011 6
1$
#18360000
0$
#18380000
1!
b11 3
b111 ?
1*
b1000 1
b1010 '
1"
b0 6
1$
#18400000
0$
#18420000
0"
b1 6
1$
#18440000
0$
#18460000
b10 6
1$
#18480000
0$
#18500000
b11 6
1$
#18520000
0$
#18540000
b100 6
1$
#18560000
0$
#18580000
b101 6
1$
#18600000
0$
#18620000
b110 6
1$
#18640000
0$
#18660000
b111 6
1$
#18680000
0$
#18700000
b1000 6
1$
#18720000
0$
#18740000
b1001 6
1$
#18760000
0$
#18780000
b1010 6
1$
#18800000
0$
#18820000
b1011 6
1$
#18840000
0$
#18860000
b1100 6
1$
#18880000
0$
#18900000
b1101 6
1$
#18920000
0$
#18940000
b1110 6
1$
#18960000
0$
#18980000
b1111 6
1$
#19000000
0$
#19020000
b10000 6
1$
#19040000
0$
#19060000
b10001 6
1$
#19080000
0$
