DFF2rx.v
module DFF2rx(
input D,clk
output reg Q
);

always @(posedge clk)
begin
    Q=D;
end

endmodule

uart_rx.v
module SIPO(
    input clk,          //driven by tick!
    input data_in,
    output a, b, c, d, e, f, g, h
);

    wire t1, t2, t3, t4, t5, t6, t7, t8;

    DFF2rx instance1(.D(data_in), .clk(clk), .Q(t1));
    DFF2rx instance2(.D(t1),.clk(clk), .Q(t2));
    DFF2rx instance3(.D(t2),.clk(clk), .Q(t3));
    DFF2rx instance4(.D(t3),.clk(clk), .Q(t4));
    DFF2rx instance5(.D(t4),.clk(clk), .Q(t5));
    DFF2rx instance6(.D(t5),.clk(clk), .Q(t6));
    DFF2rx instance7(.D(t6),.clk(clk), .Q(t7));
    DFF2rx instance8(.D(t7),.clk(clk), .Q(t8));

    assign h = t2; 
    assign g = t3; 
    assign f = t4; 
    assign e = t5;
    assign d = t6; 
    assign c = t7; 
    assign b = t8; 
    assign a = t1;
    
endmodule

baud_gen.v
module BaudGen(
    input clk,
    output reg tick
);

    reg [4:0] count = 0;                       //cuz 20 requiers 5 bit in binary 

    always @(posedge clk) 
    begin                   
        if(count >= 19)                        // 20 clock cycles per baud cuz easy for simmulation purpose
            begin
                count <= 0;
                tick <= 1;
            end 
        else 
            begin
                count <= count + 1;
                tick <= 0;
            end
    end

endmodule

FSMRX.v
module FSMRX(
    input clk,
    input rx,
    output reg Done,
    output [7:0] dataout,
    output tick
);
    wire [7:0] sipo_out;
    wire a, b, c, d, e, f, g, h;
    assign dataout = {a, b, c, d, e, f, g, h };  // LSB first

    BaudGen baudgen(.clk(clk), .tick(tick));
    SIPO sipo(.clk(tick), .data_in(rx), .a(a), .b(b), .c(c), .d(d), .e(e), .f(f), .g(g), .h(h));

    reg [2:0] state = 0;
    reg [2:0] bit_cnt = 0;

    parameter IDLE = 0, START = 1, DATA = 2, STOP = 3, DONE_STATE = 4;

    always @(posedge clk) begin
        case (state)
            IDLE: begin
                Done <= 0;
                bit_cnt <= 0;
                if (rx == 0) state <= START;
            end

            START: begin
                if (tick) state <= DATA;  // start bit sampled
            end

            DATA: begin
                if (tick) begin
                    bit_cnt <= bit_cnt + 1;
                    if (bit_cnt == 7) state <= STOP;
                end
            end

            STOP: begin
                if (tick) state <= DONE_STATE;
            end

            DONE_STATE: begin
                Done <= 1;
                state <= IDLE;
            end
        endcase
    end
endmodule

uart_tx.v
module PISO(
    input a, b, c, d, e, f, g, h,
    input clk, load, tx,
    output reg t20
);
    reg [7:0] data;
    reg [2:0] count = 0;

    always @(posedge clk) 
    begin
        if (load) 
            begin
                data <= {a, b, c, d, e, f, g, h};       // at load =1 data in parallely
                count <= 0;
            end 
        else if (~tx) 
            begin
                t20 <= data[count];                     // data transmission from lsb first to msb firstly data[0] then count inc then data[1]
                count <= count + 1;
            end
        else 
            begin
                t20 <= 1'b0;  // therefore at tx==0 output x==0 which is the start bit 
            end
    end
endmodule









// module PISO(
//     input load,a,b,c,d,e,f,g,h,clk,tx,
//     output t20
//     );
    
// wire t1,t2,t3,t6,t7,t8,t9,t10,t11,t12,t13,t14,t15,t16,t17,t18,t19;
// assign t1= ~load;
// assign t2= load;

// assign t3= clk & ~tx;

// DFF1tx instance1(.D(a), .clk(t3), .t7(t7), .in1(t2), .in2(t1), .in3(b) );
// DFF1tx instance2(.D(t7), .clk(t3), .t7(t8), .in1(t2), .in2(t1), .in3(c));
// DFF1tx instance3(.D(t8), .clk(t3), .t7(t10), .in1(t2), .in2(t1), .in3(d));
// DFF1tx instance4(.D(t10), .clk(t3), .t7(t12), .in1(t2), .in2(t1), .in3(e));
// DFF1tx instance5(.D(t12), .clk(t3), .t7(t14), .in1(t2), .in2(t1), .in3(f));
// DFF1tx instance6(.D(t14), .clk(t3), .t7(t16), .in1(t2), .in2(t1), .in3(g));
// DFF1tx instance7(.D(t16), .clk(t3), .t7(t18), .in1(t2), .in2(t1), .in3(h));
// DFF1tx instance8(.D(t18), .clk(t3), .t7(t20), .in1(1'b1), .in2(1'b0), .in3(1'b0));


// endmodule

FSMTX.v
module FSMTX(
    input clk,
    input reset,                        //for idle state to stay at idle
    input [7:0] datain,
    output Done,
    output wire x,                      //  x a wire now it can be reset to x previously it was reg that's why my ,ine 26 was not able to assign x==x it has to be continous for that
    output tick                         // Baud tick 
);

    reg tx, load;
    reg [3:0] bit_cnt;
    reg [2:0] state, nstate;

    parameter IDLE = 0, LOAD = 1, DATA = 2, STOP = 3, DONE = 4, CLEANUP = 5;

    // Internal wire to receive output from PISO
    wire t20_internal;                                  //cuz we can assign wire to x after transmission is stoped


    // instanciation of transmitter and baud gen
    BaudGen instance1(.clk(clk), .tick(tick));
    PISO instance2(.a(datain[7]), .b(datain[6]), .c(datain[5]), .d(datain[4]), .e(datain[3]), .f(datain[2]), .g(datain[1]), .h(datain[0]), .clk(tick), .load(load), .tx(tx), .t20(t20_internal));
    

    // Assign x = 'x' when tx = 1 (idle); otherwise pass data bit
    assign x = (tx == 1'b1) ? 1'bx : t20_internal;      //this stops data transmission after the stop bit

    // Next state logic acc to stat diagram
    always @(*) begin
        case (state)
            IDLE:nstate = LOAD;
            LOAD:nstate = DATA;
            DATA:nstate = (bit_cnt == 8) ? STOP : DATA;
            STOP:nstate = DONE;
            DONE:nstate = CLEANUP;
            CLEANUP: nstate = IDLE;                     //just stops data transmission after the stop bit that's why cleanup state is used
            default: nstate = IDLE;
        endcase
    end

    // conditions for the state to change there state
    always @(posedge tick or posedge reset) 
    begin
        if (reset) 
            begin                                       //reset==1 is used for idle state to stay at ideal state
                state <= IDLE;
                tx <= 1;
                load <= 0;
                bit_cnt <= 0;
            end 
        else 
            begin
                state <= nstate;
                case (state)
                    IDLE: 
                        begin
                            tx <= 1;
                            load <= 0;                  //parallel data loads into register
                            bit_cnt <= 0;
                        end
                    
                    LOAD: 
                        begin
                            tx <= 1;                    //still data transmission not started
                            load <= 1;                  //start shifting data serially
                        end

                    DATA: 
                        begin
                            tx <= 0;                    // at data stage data transmission starts
                            load <= 0;
                            bit_cnt <= bit_cnt + 1;     //data will transmit til bitcnt==8 bits then next stage
                        end

                    STOP: 
                        begin
                            tx <= 1;                    // tx==1 so data transmission stops
                        end

                    DONE: 
                        begin
                            tx <= 1;                    //same here
                        end

                    CLEANUP: 
                        begin                           //just to stop further transmission of wrong bits
                            tx <= 1;
                            load <= 0;                  
                            bit_cnt <= 0;               // bit count reset
                        end
                endcase
            end
    end

    assign Done = (state == DONE);                      // will print outpt ==1 when transmisson is done 

endmodule

topmodule.v
`timescale 1ns/1ps

module UART_TB();

    reg clk;
    reg reset;
    reg [7:0] datain;
    wire DoneTX, DoneRX;
    wire tx_line, tick_tx, tick_rx;
    wire [7:0] dataout;

    // Instantiate Transmitter
    FSMTX transmitter(
        .clk(clk),
        .reset(reset),
        .datain(datain),
        .Done(DoneTX),
        .x(tx_line),       // tx_line connected to receiver input
        .tick(tick_tx)
    );

    // Instantiate Receiver
    FSMRX receiver(
        .clk(clk),
        .rx(tx_line),      // Connected to transmitter output
        .Done(DoneRX),
        .dataout(dataout),
        .tick(tick_rx)
    );

    // Clock generation (50MHz simulation style)
    initial begin
        clk = 0;
        forever #10 clk = ~clk; // 20ns period (50 MHz)
    end

    // Test stimulus
    initial begin
        $dumpfile("uart_tb.vcd");
        $dumpvars(0, UART_TB);

        reset = 1;
        datain = 8'b00110011; // Example data to transmit
        #50 reset = 0;

        // Wait until transmitter is Done
        wait(DoneTX);
        $display("Transmitter finished sending data: %b", datain);

        // Wait until receiver is Done
        wait(DoneRX);
        $display("Receiver received data: %b", dataout);

        // Check if transmission is successful
        if(dataout == datain)
            $display("TEST PASSED: Data correctly transmitted and received!");
        else
            $display("TEST FAILED: Mismatch in transmitted and received data!");

        #100 $finish;
    end

endmodule

uart_tb.vcd
$date
	Tue Aug 26 20:55:50 2025
$end
$version
	Icarus Verilog
$end
$timescale
	1ps
$end
$scope module UART_TB $end
$var wire 1 ! tx_line $end
$var wire 1 " tick_tx $end
$var wire 1 # tick_rx $end
$var wire 8 $ dataout [7:0] $end
$var wire 1 % DoneTX $end
$var wire 1 & DoneRX $end
$var reg 1 ' clk $end
$var reg 8 ( datain [7:0] $end
$var reg 1 ) reset $end
$scope module receiver $end
$var wire 1 ' clk $end
$var wire 1 # tick $end
$var wire 1 ! rx $end
$var wire 1 * h $end
$var wire 1 + g $end
$var wire 1 , f $end
$var wire 1 - e $end
$var wire 8 . dataout [7:0] $end
$var wire 1 / d $end
$var wire 1 0 c $end
$var wire 1 1 b $end
$var wire 1 2 a $end
$var parameter 32 3 DATA $end
$var parameter 32 4 DONE_STATE $end
$var parameter 32 5 IDLE $end
$var parameter 32 6 START $end
$var parameter 32 7 STOP $end
$var reg 1 & Done $end
$var reg 3 8 bit_cnt [2:0] $end
$var reg 3 9 state [2:0] $end
$scope module baudgen $end
$var wire 1 ' clk $end
$var reg 5 : count [4:0] $end
$var reg 1 # tick $end
$upscope $end
$scope module sipo $end
$var wire 1 2 a $end
$var wire 1 1 b $end
$var wire 1 0 c $end
$var wire 1 # clk $end
$var wire 1 / d $end
$var wire 1 - e $end
$var wire 1 , f $end
$var wire 1 + g $end
$var wire 1 * h $end
$var wire 1 ; t8 $end
$var wire 1 < t7 $end
$var wire 1 = t6 $end
$var wire 1 > t5 $end
$var wire 1 ? t4 $end
$var wire 1 @ t3 $end
$var wire 1 A t2 $end
$var wire 1 B t1 $end
$var wire 1 ! data_in $end
$scope module instance1 $end
$var wire 1 # clk $end
$var wire 1 ! D $end
$var reg 1 B Q $end
$upscope $end
$scope module instance2 $end
$var wire 1 B D $end
$var wire 1 # clk $end
$var reg 1 A Q $end
$upscope $end
$scope module instance3 $end
$var wire 1 A D $end
$var wire 1 # clk $end
$var reg 1 @ Q $end
$upscope $end
$scope module instance4 $end
$var wire 1 @ D $end
$var wire 1 # clk $end
$var reg 1 ? Q $end
$upscope $end
$scope module instance5 $end
$var wire 1 ? D $end
$var wire 1 # clk $end
$var reg 1 > Q $end
$upscope $end
$scope module instance6 $end
$var wire 1 > D $end
$var wire 1 # clk $end
$var reg 1 = Q $end
$upscope $end
$scope module instance7 $end
$var wire 1 = D $end
$var wire 1 # clk $end
$var reg 1 < Q $end
$upscope $end
$scope module instance8 $end
$var wire 1 < D $end
$var wire 1 # clk $end
$var reg 1 ; Q $end
$upscope $end
$upscope $end
$upscope $end
$scope module transmitter $end
$var wire 1 ' clk $end
$var wire 8 C datain [7:0] $end
$var wire 1 ) reset $end
$var wire 1 ! x $end
$var wire 1 " tick $end
$var wire 1 D t20_internal $end
$var wire 1 % Done $end
$var parameter 32 E CLEANUP $end
$var parameter 32 F DATA $end
$var parameter 32 G DONE $end
$var parameter 32 H IDLE $end
$var parameter 32 I LOAD $end
$var parameter 32 J STOP $end
$var reg 4 K bit_cnt [3:0] $end
$var reg 1 L load $end
$var reg 3 M nstate [2:0] $end
$var reg 3 N state [2:0] $end
$var reg 1 O tx $end
$scope module instance1 $end
$var wire 1 ' clk $end
$var reg 5 P count [4:0] $end
$var reg 1 " tick $end
$upscope $end
$scope module instance2 $end
$var wire 1 Q a $end
$var wire 1 R b $end
$var wire 1 S c $end
$var wire 1 " clk $end
$var wire 1 T d $end
$var wire 1 U e $end
$var wire 1 V f $end
$var wire 1 W g $end
$var wire 1 X h $end
$var wire 1 L load $end
$var wire 1 O tx $end
$var reg 3 Y count [2:0] $end
$var reg 8 Z data [7:0] $end
$var reg 1 D t20 $end
$upscope $end
$upscope $end
$upscope $end
$enddefinitions $end
$comment Show the parameter values. $end
$dumpall
b11 J
b1 I
b0 H
b100 G
b10 F
b101 E
b11 7
b1 6
b0 5
b100 4
b10 3
$end
#0
$dumpvars
bx Z
b0 Y
1X
1W
0V
0U
1T
1S
0R
0Q
b0 P
1O
b0 N
b1 M
0L
b0 K
xD
b110011 C
xB
xA
x@
x?
x>
x=
x<
x;
b0 :
b0 9
b0 8
x2
x1
x0
x/
bx .
x-
x,
x+
x*
1)
b110011 (
0'
x&
0%
bx $
x#
x"
1!
$end
#10000
0"
b1 P
0#
b1 :
0&
1'
#20000
0'
#30000
b10 :
b10 P
1'
#40000
0'
#50000
b11 P
b11 :
1'
0)
#60000
0'
#70000
b100 :
b100 P
1'
#80000
0'
#90000
b101 P
b101 :
1'
#100000
0'
#110000
b110 :
b110 P
1'
#120000
0'
#130000
b111 P
b111 :
1'
#140000
0'
#150000
b1000 :
b1000 P
1'
#160000
0'
#170000
b1001 P
b1001 :
1'
#180000
0'
#190000
b1010 :
b1010 P
1'
#200000
0'
#210000
b1011 P
b1011 :
1'
#220000
0'
#230000
b1100 :
b1100 P
1'
#240000
0'
#250000
b1101 P
b1101 :
1'
#260000
0'
#270000
b1110 :
b1110 P
1'
#280000
0'
#290000
b1111 P
b1111 :
1'
#300000
0'
#310000
b10000 :
b10000 P
1'
#320000
0'
#330000
b10001 P
b10001 :
1'
#340000
0'
#350000
b10010 :
b10010 P
1'
#360000
0'
#370000
b10011 P
b10011 :
1'
#380000
0'
#390000
b10 M
bx1 $
bx1 .
12
1B
0D
b1 N
1#
b0 :
1"
b0 P
1'
#400000
0'
#410000
0"
b1 P
0#
b1 :
1'
#420000
0'
#430000
b10 :
b10 P
1'
#440000
0'
#450000
b11 P
b11 :
1'
#460000
0'
#470000
b100 :
b100 P
1'
#480000
0'
#490000
b101 P
b101 :
1'
#500000
0'
#510000
b110 :
b110 P
1'
#520000
0'
#530000
b111 P
b111 :
1'
#540000
0'
#550000
b1000 :
b1000 P
1'
#560000
0'
#570000
b1001 P
b1001 :
1'
#580000
0'
#590000
b1010 :
b1010 P
1'
#600000
0'
#610000
b1011 P
b1011 :
1'
#620000
0'
#630000
b1100 :
b1100 P
1'
#640000
0'
#650000
b1101 P
b1101 :
1'
#660000
0'
#670000
b1110 :
b1110 P
1'
#680000
0'
#690000
b1111 P
b1111 :
1'
#700000
0'
#710000
b10000 :
b10000 P
1'
#720000
0'
#730000
b10001 P
b10001 :
1'
#740000
0'
#750000
b10010 :
b10010 P
1'
#760000
0'
#770000
b10011 P
b10011 :
1'
#780000
0'
#790000
b1xxxxxx1 $
b1xxxxxx1 .
1*
1A
1L
b10 N
1#
b0 :
1"
b0 P
1'
#800000
0'
#810000
0"
b1 P
0#
b1 :
1'
#820000
0'
#830000
b10 :
b10 P
1'
#840000
0'
#850000
b11 P
b11 :
1'
#860000
0'
#870000
b100 :
b100 P
1'
#880000
0'
#890000
b101 P
b101 :
1'
#900000
0'
#910000
b110 :
b110 P
1'
#920000
0'
#930000
b111 P
b111 :
1'
#940000
0'
#950000
b1000 :
b1000 P
1'
#960000
0'
#970000
b1001 P
b1001 :
1'
#980000
0'
#990000
b1010 :
b1010 P
1'
#1000000
0'
#1010000
b1011 P
b1011 :
1'
#1020000
0'
#1030000
b1100 :
b1100 P
1'
#1040000
0'
#1050000
b1101 P
b1101 :
1'
#1060000
0'
#1070000
b1110 :
b1110 P
1'
#1080000
0'
#1090000
b1111 P
b1111 :
1'
#1100000
0'
#1110000
b10000 :
b10000 P
1'
#1120000
0'
#1130000
b10001 P
b10001 :
1'
#1140000
0'
#1150000
b10010 :
b10010 P
1'
#1160000
0'
#1170000
b10011 P
b10011 :
1'
#1180000
0'
#1190000
0!
b11xxxxx1 $
b11xxxxx1 .
1+
1@
b110011 Z
b1 K
0L
0O
1#
b0 :
1"
b0 P
1'
#1200000
0'
#1210000
0"
b1 P
0#
b1 :
b1 9
1'
#1220000
0'
#1230000
b10 :
b10 P
1'
#1240000
0'
#1250000
b11 P
b11 :
1'
#1260000
0'
#1270000
b100 :
b100 P
1'
#1280000
0'
#1290000
b101 P
b101 :
1'
#1300000
0'
#1310000
b110 :
b110 P
1'
#1320000
0'
#1330000
b111 P
b111 :
1'
#1340000
0'
#1350000
b1000 :
b1000 P
1'
#1360000
0'
#1370000
b1001 P
b1001 :
1'
#1380000
0'
#1390000
b1010 :
b1010 P
1'
#1400000
0'
#1410000
b1011 P
b1011 :
1'
#1420000
0'
#1430000
b1100 :
b1100 P
1'
#1440000
0'
#1450000
b1101 P
b1101 :
1'
#1460000
0'
#1470000
b1110 :
b1110 P
1'
#1480000
0'
#1490000
b1111 P
b1111 :
1'
#1500000
0'
#1510000
b10000 :
b10000 P
1'
#1520000
0'
#1530000
b10001 P
b10001 :
1'
#1540000
0'
#1550000
b10010 :
b10010 P
1'
#1560000
0'
#1570000
b10011 P
b10011 :
1'
#1580000
0'
#1590000
1!
1,
1?
b111xxxx0 $
b111xxxx0 .
02
0B
b1 Y
1D
b10 K
1#
b0 :
1"
b0 P
1'
#1600000
0'
#1610000
0"
b1 P
0#
b1 :
b10 9
1'
#1620000
0'
#1630000
b10 :
b10 P
1'
#1640000
0'
#1650000
b11 P
b11 :
1'
#1660000
0'
#1670000
b100 :
b100 P
1'
#1680000
0'
#1690000
b101 P
b101 :
1'
#1700000
0'
#1710000
b110 :
b110 P
1'
#1720000
0'
#1730000
b111 P
b111 :
1'
#1740000
0'
#1750000
b1000 :
b1000 P
1'
#1760000
0'
#1770000
b1001 P
b1001 :
1'
#1780000
0'
#1790000
b1010 :
b1010 P
1'
#1800000
0'
#1810000
b1011 P
b1011 :
1'
#1820000
0'
#1830000
b1100 :
b1100 P
1'
#1840000
0'
#1850000
b1101 P
b1101 :
1'
#1860000
0'
#1870000
b1110 :
b1110 P
1'
#1880000
0'
#1890000
b1111 P
b1111 :
1'
#1900000
0'
#1910000
b10000 :
b10000 P
1'
#1920000
0'
#1930000
b10001 P
b10001 :
1'
#1940000
0'
#1950000
b10010 :
b10010 P
1'
#1960000
0'
#1970000
b10011 P
b10011 :
1'
#1980000
0'
#1990000
12
1B
0*
0A
b111xxx1 $
b111xxx1 .
1-
1>
b10 Y
b11 K
1#
b0 :
1"
b0 P
1'
#2000000
0'
#2010000
0"
b1 P
0#
b1 :
b1 8
1'
#2020000
0'
#2030000
b10 :
b10 P
1'
#2040000
0'
#2050000
b11 P
b11 :
1'
#2060000
0'
#2070000
b100 :
b100 P
1'
#2080000
0'
#2090000
b101 P
b101 :
1'
#2100000
0'
#2110000
b110 :
b110 P
1'
#2120000
0'
#2130000
b111 P
b111 :
1'
#2140000
0'
#2150000
b1000 :
b1000 P
1'
#2160000
0'
#2170000
b1001 P
b1001 :
1'
#2180000
0'
#2190000
b1010 :
b1010 P
1'
#2200000
0'
#2210000
b1011 P
b1011 :
1'
#2220000
0'
#2230000
b1100 :
b1100 P
1'
#2240000
0'
#2250000
b1101 P
b1101 :
1'
#2260000
0'
#2270000
b1110 :
b1110 P
1'
#2280000
0'
#2290000
b1111 P
b1111 :
1'
#2300000
0'
#2310000
b10000 :
b10000 P
1'
#2320000
0'
#2330000
b10001 P
b10001 :
1'
#2340000
0'
#2350000
b10010 :
b10010 P
1'
#2360000
0'
#2370000
b10011 P
b10011 :
1'
#2380000
0'
#2390000
0!
1/
1=
0+
0@
b10111xx1 $
b10111xx1 .
1*
1A
b11 Y
0D
b100 K
1#
b0 :
1"
b0 P
1'
#2400000
0'
#2410000
0"
b1 P
0#
b1 :
b10 8
1'
#2420000
0'
#2430000
b10 :
b10 P
1'
#2440000
0'
#2450000
b11 P
b11 :
1'
#2460000
0'
#2470000
b100 :
b100 P
1'
#2480000
0'
#2490000
b101 P
b101 :
1'
#2500000
0'
#2510000
b110 :
b110 P
1'
#2520000
0'
#2530000
b111 P
b111 :
1'
#2540000
0'
#2550000
b1000 :
b1000 P
1'
#2560000
0'
#2570000
b1001 P
b1001 :
1'
#2580000
0'
#2590000
b1010 :
b1010 P
1'
#2600000
0'
#2610000
b1011 P
b1011 :
1'
#2620000
0'
#2630000
b1100 :
b1100 P
1'
#2640000
0'
#2650000
b1101 P
b1101 :
1'
#2660000
0'
#2670000
b1110 :
b1110 P
1'
#2680000
0'
#2690000
b1111 P
b1111 :
1'
#2700000
0'
#2710000
b10000 :
b10000 P
1'
#2720000
0'
#2730000
b10001 P
b10001 :
1'
#2740000
0'
#2750000
b10010 :
b10010 P
1'
#2760000
0'
#2770000
b10011 P
b10011 :
1'
#2780000
0'
#2790000
02
0B
1+
1@
0,
0?
b110111x0 $
b110111x0 .
10
1<
b100 Y
b101 K
1#
b0 :
1"
b0 P
1'
#2800000
0'
#2810000
0"
b1 P
0#
b1 :
b11 8
1'
#2820000
0'
#2830000
b10 :
b10 P
1'
#2840000
0'
#2850000
b11 P
b11 :
1'
#2860000
0'
#2870000
b100 :
b100 P
1'
#2880000
0'
#2890000
b101 P
b101 :
1'
#2900000
0'
#2910000
b110 :
b110 P
1'
#2920000
0'
#2930000
b111 P
b111 :
1'
#2940000
0'
#2950000
b1000 :
b1000 P
1'
#2960000
0'
#2970000
b1001 P
b1001 :
1'
#2980000
0'
#2990000
b1010 :
b1010 P
1'
#3000000
0'
#3010000
b1011 P
b1011 :
1'
#3020000
0'
#3030000
b1100 :
b1100 P
1'
#3040000
0'
#3050000
b1101 P
b1101 :
1'
#3060000
0'
#3070000
b1110 :
b1110 P
1'
#3080000
0'
#3090000
b1111 P
b1111 :
1'
#3100000
0'
#3110000
b10000 :
b10000 P
1'
#3120000
0'
#3130000
b10001 P
b10001 :
1'
#3140000
0'
#3150000
b10010 :
b10010 P
1'
#3160000
0'
#3170000
b10011 P
b10011 :
1'
#3180000
0'
#3190000
1!
11
1;
0-
0>
1,
1?
b1101110 $
b1101110 .
0*
0A
b101 Y
1D
b110 K
1#
b0 :
1"
b0 P
1'
#3200000
0'
#3210000
0"
b1 P
0#
b1 :
b100 8
1'
#3220000
0'
#3230000
b10 :
b10 P
1'
#3240000
0'
#3250000
b11 P
b11 :
1'
#3260000
0'
#3270000
b100 :
b100 P
1'
#3280000
0'
#3290000
b101 P
b101 :
1'
#3300000
0'
#3310000
b110 :
b110 P
1'
#3320000
0'
#3330000
b111 P
b111 :
1'
#3340000
0'
#3350000
b1000 :
b1000 P
1'
#3360000
0'
#3370000
b1001 P
b1001 :
1'
#3380000
0'
#3390000
b1010 :
b1010 P
1'
#3400000
0'
#3410000
b1011 P
b1011 :
1'
#3420000
0'
#3430000
b1100 :
b1100 P
1'
#3440000
0'
#3450000
b1101 P
b1101 :
1'
#3460000
0'
#3470000
b1110 :
b1110 P
1'
#3480000
0'
#3490000
b1111 P
b1111 :
1'
#3500000
0'
#3510000
b10000 :
b10000 P
1'
#3520000
0'
#3530000
b10001 P
b10001 :
1'
#3540000
0'
#3550000
b10010 :
b10010 P
1'
#3560000
0'
#3570000
b10011 P
b10011 :
1'
#3580000
0'
#3590000
12
1B
0+
0@
1-
1>
b110111 $
b110111 .
0/
0=
b110 Y
b111 K
1#
b0 :
1"
b0 P
1'
#3600000
0'
#3610000
0"
b1 P
0#
b1 :
b101 8
1'
#3620000
0'
#3630000
b10 :
b10 P
1'
#3640000
0'
#3650000
b11 P
b11 :
1'
#3660000
0'
#3670000
b100 :
b100 P
1'
#3680000
0'
#3690000
b101 P
b101 :
1'
#3700000
0'
#3710000
b110 :
b110 P
1'
#3720000
0'
#3730000
b111 P
b111 :
1'
#3740000
0'
#3750000
b1000 :
b1000 P
1'
#3760000
0'
#3770000
b1001 P
b1001 :
1'
#3780000
0'
#3790000
b1010 :
b1010 P
1'
#3800000
0'
#3810000
b1011 P
b1011 :
1'
#3820000
0'
#3830000
b1100 :
b1100 P
1'
#3840000
0'
#3850000
b1101 P
b1101 :
1'
#3860000
0'
#3870000
b1110 :
b1110 P
1'
#3880000
0'
#3890000
b1111 P
b1111 :
1'
#3900000
0'
#3910000
b10000 :
b10000 P
1'
#3920000
0'
#3930000
b10001 P
b10001 :
1'
#3940000
0'
#3950000
b10010 :
b10010 P
1'
#3960000
0'
#3970000
b10011 P
b10011 :
1'
#3980000
0'
#3990000
0!
b11 M
00
0<
1/
1=
0,
0?
b10011011 $
b10011011 .
1*
1A
b111 Y
0D
b1000 K
1#
b0 :
1"
b0 P
1'
#4000000
0'
#4010000
0"
b1 P
0#
b1 :
b110 8
1'
#4020000
0'
#4030000
b10 :
b10 P
1'
#4040000
0'
#4050000
b11 P
b11 :
1'
#4060000
0'
#4070000
b100 :
b100 P
1'
#4080000
0'
#4090000
b101 P
b101 :
1'
#4100000
0'
#4110000
b110 :
b110 P
1'
#4120000
0'
#4130000
b111 P
b111 :
1'
#4140000
0'
#4150000
b1000 :
b1000 P
1'
#4160000
0'
#4170000
b1001 P
b1001 :
1'
#4180000
0'
#4190000
b1010 :
b1010 P
1'
#4200000
0'
#4210000
b1011 P
b1011 :
1'
#4220000
0'
#4230000
b1100 :
b1100 P
1'
#4240000
0'
#4250000
b1101 P
b1101 :
1'
#4260000
0'
#4270000
b1110 :
b1110 P
1'
#4280000
0'
#4290000
b1111 P
b1111 :
1'
#4300000
0'
#4310000
b10000 :
b10000 P
1'
#4320000
0'
#4330000
b10001 P
b10001 :
1'
#4340000
0'
#4350000
b10010 :
b10010 P
1'
#4360000
0'
#4370000
b10011 P
b10011 :
1'
#4380000
0'
#4390000
b100 M
02
0B
1+
1@
0-
0>
10
1<
b11001100 $
b11001100 .
01
0;
b0 Y
b1001 K
b11 N
1#
b0 :
1"
b0 P
1'
#4400000
0'
#4410000
0"
b1 P
0#
b1 :
b111 8
1'
#4420000
0'
#4430000
b10 :
b10 P
1'
#4440000
0'
#4450000
b11 P
b11 :
1'
#4460000
0'
#4470000
b100 :
b100 P
1'
#4480000
0'
#4490000
b101 P
b101 :
1'
#4500000
0'
#4510000
b110 :
b110 P
1'
#4520000
0'
#4530000
b111 P
b111 :
1'
#4540000
0'
#4550000
b1000 :
b1000 P
1'
#4560000
0'
#4570000
b1001 P
b1001 :
1'
#4580000
0'
#4590000
b1010 :
b1010 P
1'
#4600000
0'
#4610000
b1011 P
b1011 :
1'
#4620000
0'
#4630000
b1100 :
b1100 P
1'
#4640000
0'
#4650000
b1101 P
b1101 :
1'
#4660000
0'
#4670000
b1110 :
b1110 P
1'
#4680000
0'
#4690000
b1111 P
b1111 :
1'
#4700000
0'
#4710000
b10000 :
b10000 P
1'
#4720000
0'
#4730000
b10001 P
b10001 :
1'
#4740000
0'
#4750000
b10010 :
b10010 P
1'
#4760000
0'
#4770000
b10011 P
b10011 :
1'
#4780000
0'
#4790000
1!
b101 M
11
1;
0/
0=
1,
1?
b1100110 $
b1100110 .
0*
0A
b1 Y
1D
1O
1%
b100 N
1#
b0 :
1"
b0 P
1'
#4800000
0'
#4810000
0"
b1 P
0#
b1 :
b11 9
1'
#4820000
0'
#4830000
b10 :
b10 P
1'
#4840000
0'
#4850000
b11 P
b11 :
1'
#4860000
0'
#4870000
b100 :
b100 P
1'
#4880000
0'
#4890000
b101 P
b101 :
1'
#4900000
0'
#4910000
b110 :
b110 P
1'
#4920000
0'
#4930000
b111 P
b111 :
1'
#4940000
0'
#4950000
b1000 :
b1000 P
1'
#4960000
0'
#4970000
b1001 P
b1001 :
1'
#4980000
0'
#4990000
b1010 :
b1010 P
1'
#5000000
0'
#5010000
b1011 P
b1011 :
1'
#5020000
0'
#5030000
b1100 :
b1100 P
1'
#5040000
0'
#5050000
b1101 P
b1101 :
1'
#5060000
0'
#5070000
b1110 :
b1110 P
1'
#5080000
0'
#5090000
b1111 P
b1111 :
1'
#5100000
0'
#5110000
b10000 :
b10000 P
1'
#5120000
0'
#5130000
b10001 P
b10001 :
1'
#5140000
0'
#5150000
b10010 :
b10010 P
1'
#5160000
0'
#5170000
b10011 P
b10011 :
1'
#5180000
0'
#5190000
b0 M
12
1B
0+
0@
1-
1>
b110011 $
b110011 .
00
0<
0D
0%
b101 N
1#
b0 :
1"
b0 P
1'
#5200000
0'
#5210000
0"
b1 P
0#
b1 :
b100 9
1'
#5220000
0'
#5230000
b0 9
1&
b10 :
b10 P
1'
#5240000
0'
#5250000
b11 P
b11 :
b0 8
0&
1'
#5260000
0'
#5270000
b100 :
b100 P
1'
#5280000
0'
#5290000
b101 P
b101 :
1'
#5300000
0'
#5310000
b110 :
b110 P
1'
#5320000
0'
#5330000
b111 P
b111 :
1'
